[{"pdCode":null,"balance":null,"createdBy":null,"createdDate":null,"deleted":false,"discount":null,"dueDate":null,"purExpTotal":null,"paid":null,"vouDate":"20/12/2021","remark":null,"sessionId":null,"updatedBy":null,"updatedDate":null,"vouTotal":null,"curCode":null,"traderCode":"SUP00001-009","discountPrice":null,"taxPrice":null,"taxAmount":null,"intgUpdStatus":null,"macId":null,"compCode":null,"vouNo":"1100001-12-2021","stockCode":null,"expDate":null,"qty":10.0,"stdWt":null,"avgPrice":null,"purUnit":"kg","avgWt":1.0,"purPrice":3000.0,"purAmount":30000.0,"locationCode":null,"uniqueId":null,"createdName":null,"updatedName":null,"curName":null,"traderName":"YNE","locationName":null,"compName":"Sanhe Tissue Paper","compPhone":null,"compAddress":null,"stockName":"Plain Packing Bag"},{"pdCode":null,"balance":null,"createdBy":null,"createdDate":null,"deleted":false,"discount":null,"dueDate":null,"purExpTotal":null,"paid":null,"vouDate":"20/12/2021","remark":null,"sessionId":null,"updatedBy":null,"updatedDate":null,"vouTotal":null,"curCode":null,"traderCode":"SUP00001-009","discountPrice":null,"taxPrice":null,"taxAmount":null,"intgUpdStatus":null,"macId":null,"compCode":null,"vouNo":"1100004-12-2021","stockCode":null,"expDate":null,"qty":15.0,"stdWt":null,"avgPrice":null,"purUnit":"kg","avgWt":1.0,"purPrice":3000.0,"purAmount":45000.0,"locationCode":null,"uniqueId":null,"createdName":null,"updatedName":null,"curName":null,"traderName":"YNE","locationName":null,"compName":"Sanhe Tissue Paper","compPhone":null,"compAddress":null,"stockName":"Plain Packing Bag"},{"pdCode":null,"balance":null,"createdBy":null,"createdDate":null,"deleted":false,"discount":null,"dueDate":null,"purExpTotal":null,"paid":null,"vouDate":"20/12/2021","remark":null,"sessionId":null,"updatedBy":null,"updatedDate":null,"vouTotal":null,"curCode":null,"traderCode":"SUP00002-009","discountPrice":null,"taxPrice":null,"taxAmount":null,"intgUpdStatus":null,"macId":null,"compCode":null,"vouNo":"1100002-12-2021","stockCode":null,"expDate":null,"qty":5.0,"stdWt":null,"avgPrice":null,"purUnit":"pcs","avgWt":1.0,"purPrice":5000.0,"purAmount":25000.0,"locationCode":null,"uniqueId":null,"createdName":null,"updatedName":null,"curName":null,"traderName":"Pan Thazin","locationName":null,"compName":"Sanhe Tissue Paper","compPhone":null,"compAddress":null,"stockName":"Plain Tissue 100*90mm *2ply"}]