[{"deleted":false,"vouDate":"28/01/2022","remark":"4D-6805","traderCode":"SUP00006-019","vouNo":"2100003-032022","purAmount":2.7718E7,"traderName":"APP China"},{"deleted":false,"vouDate":"28/01/2022","remark":"00006","traderCode":"SUP00006-019","vouNo":"2100002-032022","purAmount":2.7718E7,"traderName":"APP China"},{"deleted":false,"vouDate":"26/01/2022","remark":"SR-00002","traderCode":"SUP00005-019","vouNo":"1600001-022022","purAmount":130000.0,"traderName":"Aung - Digital Printing Service"},{"deleted":false,"vouDate":"18/01/2022","remark":"","traderCode":"SUP00002-012","vouNo":"1900003-012022","purAmount":2304900.0,"traderName":"Golden Heir"},{"deleted":false,"vouDate":"29/01/2022","remark":"SR-00007","traderCode":"SUP00002-012","vouNo":"1900005-012022","purAmount":182800.0,"traderName":"Golden Heir"},{"deleted":false,"vouDate":"29/01/2022","remark":"SR-00007","traderCode":"SUP00002-012","vouNo":"1900006-012022","purAmount":856950.0,"traderName":"Golden Heir"},{"deleted":false,"vouDate":"22/01/2022","remark":"","traderCode":"SUP00001-018","vouNo":"1800003-012022","purAmount":150750.0,"traderName":"Shwe Lat Yay"},{"deleted":false,"vouDate":"26/01/2022","remark":"0310","traderCode":"SUP00001-018","vouNo":"1800004-012022","purAmount":205000.0,"traderName":"Shwe Lat Yay"},{"deleted":false,"vouDate":"05/01/2022","remark":"4452","traderCode":"SUP00001-011","vouNo":"1800002-012022","purAmount":1225000.0,"traderName":"Tissue World"},{"deleted":false,"vouDate":"23/01/2022","remark":"3946","traderCode":"SUP00001-012","vouNo":"1900002-012022","purAmount":2112500.0,"traderName":"Tun Yar Zar"},{"deleted":false,"vouDate":"23/01/2022","remark":"SR - 3945","traderCode":"SUP00001-012","vouNo":"1900001-012022","purAmount":2297500.0,"traderName":"Tun Yar Zar"},{"deleted":false,"vouDate":"26/01/2022","remark":"SR-00001","traderCode":"SUP00001-009","vouNo":"1900007-012022","purAmount":2639622.8,"traderName":"Yangon New Epoch Packing Industry Co,.Ltd"},{"deleted":false,"vouDate":"05/01/2022","remark":"SR-3932","traderCode":"SUP00007-019","vouNo":"1900006-022022","purAmount":73842.0,"traderName":"Zuo Zong (cai gou)"}]