[{"key":{"brandCode":"09-001","compCode":"0010010","deptId":1},"brandName":"1bag*12pk*12pcs","updatedDate":"Friday, August 20, 2021 at 3:37:56 PM Myanmar Time","updatedBy":"1","createdDate":"Friday, August 20, 2021 at 9:07:56 AM Myanmar Time","createdBy":"1","macId":9,"userCode":"01"},{"key":{"brandCode":"09-002","compCode":"0010010","deptId":1},"brandName":"1bag*10pk*10pcs","updatedDate":"Friday, August 20, 2021 at 3:38:03 PM Myanmar Time","updatedBy":"1","createdDate":"Friday, August 20, 2021 at 9:08:03 AM Myanmar Time","createdBy":"1","macId":9,"userCode":"02"},{"key":{"brandCode":"09-003","compCode":"0010010","deptId":1},"brandName":"1bag*8pk*10pcs","updatedDate":"Monday, July 12, 2021 at 9:52:40 AM Myanmar Time","updatedBy":"1","createdDate":"Monday, July 12, 2021 at 3:22:40 AM Myanmar Time","createdBy":"1","macId":9,"userCode":"03"},{"key":{"brandCode":"09-004","compCode":"0010010","deptId":1},"brandName":"1bag*18pk*6pcs","updatedDate":"Friday, August 20, 2021 at 3:42:52 PM Myanmar Time","updatedBy":"1","createdDate":"Friday, August 20, 2021 at 9:08:09 AM Myanmar Time","createdBy":"1","macId":9,"userCode":"05"},{"key":{"brandCode":"09-005","compCode":"0010010","deptId":1},"brandName":"1bag*8pk*12pcs","updatedDate":"Friday, August 20, 2021 at 3:42:45 PM Myanmar Time","updatedBy":"1","createdDate":"Friday, August 20, 2021 at 9:12:44 AM Myanmar Time","createdBy":"1","macId":9,"userCode":"07"},{"key":{"brandCode":"09-006","compCode":"0010010","deptId":1},"brandName":"1box*40pk*16pcs","updatedDate":"Sunday, September 26, 2021 at 9:30:26 AM Myanmar Time","updatedBy":"1","createdDate":"Sunday, September 26, 2021 at 3:00:26 AM Myanmar Time","createdBy":"1","macId":9,"userCode":"09"},{"key":{"brandCode":"09-007","compCode":"0010010","deptId":1},"brandName":"1bag*120pcs","updatedDate":"Sunday, September 26, 2021 at 10:59:41 AM Myanmar Time","updatedBy":"1","createdDate":"Sunday, September 26, 2021 at 4:29:41 AM Myanmar Time","createdBy":"1","macId":9,"userCode":"08"},{"key":{"brandCode":"10-001","compCode":"0010010","deptId":1},"brandName":"1box*8pk*4pcs","updatedDate":"Sunday, August 22, 2021 at 1:07:20 PM Myanmar Time","updatedBy":"1","createdDate":"Sunday, August 22, 2021 at 6:37:18 AM Myanmar Time","createdBy":"1","macId":10,"userCode":"10"},{"key":{"brandCode":"10-002","compCode":"0010010","deptId":1},"brandName":"1bag*8pk*20pcs","updatedDate":"Wednesday, August 25, 2021 at 4:26:46 PM Myanmar Time","updatedBy":"1","createdDate":"Wednesday, August 25, 2021 at 9:56:44 AM Myanmar Time","createdBy":"1","macId":10,"userCode":"04"},{"key":{"brandCode":"10-003","compCode":"0010010","deptId":1},"brandName":"1bag*40pk*2Rolls","updatedDate":"Thursday, August 26, 2021 at 5:21:43 PM Myanmar Time","updatedBy":"1","createdDate":"Thursday, August 26, 2021 at 10:51:41 AM Myanmar Time","createdBy":"1","macId":10,"userCode":"12"},{"key":{"brandCode":"10-004","compCode":"0010010","deptId":1},"brandName":"1bag*30pk*3pcs","updatedDate":"Thursday, August 26, 2021 at 6:02:39 PM Myanmar Time","updatedBy":"1","createdDate":"Thursday, August 26, 2021 at 11:32:37 AM Myanmar Time","createdBy":"1","macId":10,"userCode":"11"},{"key":{"brandCode":"11-001","compCode":"0010010","deptId":1},"brandName":"1box*12pcs","updatedDate":"Friday, December 17, 2021 at 3:37:41 PM Myanmar Time","updatedBy":"1","createdDate":"Friday, December 17, 2021 at 8:58:49 AM Myanmar Time","createdBy":"1","macId":11,"userCode":"13"},{"key":{"brandCode":"11-002","compCode":"0010010","deptId":1},"brandName":"1bag*18pk*3pcs","updatedDate":"Friday, December 17, 2021 at 3:29:51 PM Myanmar Time","createdDate":"Friday, December 17, 2021 at 8:59:51 AM Myanmar Time","createdBy":"1","macId":11,"userCode":"06"},{"key":{"brandCode":"11-003","compCode":"0010010","deptId":1},"brandName":"1bag*600pcs","updatedDate":"Saturday, December 18, 2021 at 10:39:02 AM Myanmar Time","createdDate":"Saturday, December 18, 2021 at 4:09:02 AM Myanmar Time","createdBy":"1","macId":11,"userCode":"14"},{"key":{"brandCode":"11-004","compCode":"0010010","deptId":1},"brandName":"1box*6pk*5pcs","updatedDate":"Saturday, December 18, 2021 at 11:06:27 AM Myanmar Time","updatedBy":"1","createdDate":"Saturday, December 18, 2021 at 4:35:38 AM Myanmar Time","createdBy":"1","macId":11,"userCode":"15"},{"key":{"brandCode":"11-005","compCode":"0010010","deptId":1},"brandName":"1bag*84pcs","updatedDate":"Saturday, December 18, 2021 at 11:21:23 AM Myanmar Time","createdDate":"Saturday, December 18, 2021 at 4:51:23 AM Myanmar Time","createdBy":"1","macId":11,"userCode":"16"},{"key":{"brandCode":"11-006","compCode":"0010010","deptId":1},"brandName":"1bag*200kg","updatedDate":"Saturday, December 18, 2021 at 2:22:56 PM Myanmar Time","createdDate":"Saturday, December 18, 2021 at 7:52:56 AM Myanmar Time","createdBy":"1","macId":11,"userCode":"R-01"},{"key":{"brandCode":"11-007","compCode":"0010010","deptId":1},"brandName":"1bag*170kg","updatedDate":"Saturday, December 18, 2021 at 2:30:20 PM Myanmar Time","updatedBy":"1","createdDate":"Saturday, December 18, 2021 at 8:00:12 AM Myanmar Time","createdBy":"1","macId":11,"userCode":"R-02"},{"key":{"brandCode":"11-008","compCode":"0010010","deptId":1},"brandName":"1pk*50pcs","updatedDate":"Saturday, December 18, 2021 at 3:14:25 PM Myanmar Time","createdDate":"Saturday, December 18, 2021 at 8:44:25 AM Myanmar Time","createdBy":"1","macId":11,"userCode":"PK-001"},{"key":{"brandCode":"11-009","compCode":"0010010","deptId":1},"brandName":"1PK*10PCS","updatedDate":"Sunday, December 19, 2021 at 10:32:39 AM Myanmar Time","updatedBy":"1","createdDate":"Sunday, December 19, 2021 at 4:02:15 AM Myanmar Time","createdBy":"1","macId":11,"userCode":"PK-002"},{"key":{"brandCode":"11-010","compCode":"0010010","deptId":1},"brandName":"1bag*10pk*3pcs","updatedDate":"Sunday, December 19, 2021 at 11:31:06 AM Myanmar Time","updatedBy":"1","createdDate":"Sunday, December 19, 2021 at 5:01:06 AM Myanmar Time","createdBy":"1","macId":11,"userCode":"24"},{"key":{"brandCode":"11-011","compCode":"0010010","deptId":1},"brandName":"1PK*30PCS","updatedDate":"Sunday, December 19, 2021 at 11:39:46 AM Myanmar Time","createdDate":"Sunday, December 19, 2021 at 5:09:46 AM Myanmar Time","createdBy":"1","macId":11,"userCode":"PK-003"},{"key":{"brandCode":"11-012","compCode":"0010010","deptId":1},"brandName":"1PK*100PCS","updatedDate":"Sunday, December 19, 2021 at 11:44:59 AM Myanmar Time","createdDate":"Sunday, December 19, 2021 at 5:14:59 AM Myanmar Time","createdBy":"1","macId":11,"userCode":"PK-004"},{"key":{"brandCode":"11-013","compCode":"0010010","deptId":1},"brandName":"1PK*20PCS","updatedDate":"Sunday, December 19, 2021 at 1:06:52 PM Myanmar Time","createdDate":"Sunday, December 19, 2021 at 6:36:52 AM Myanmar Time","createdBy":"1","macId":11,"userCode":"PK-005"},{"key":{"brandCode":"11-014","compCode":"0010010","deptId":1},"brandName":"1PK*690PCS","updatedDate":"Sunday, December 19, 2021 at 2:30:57 PM Myanmar Time","updatedBy":"1","createdDate":"Sunday, December 19, 2021 at 7:43:19 AM Myanmar Time","createdBy":"1","macId":11,"userCode":"PK-006"},{"key":{"brandCode":"11-015","compCode":"0010010","deptId":1},"brandName":"1PK*67PCS","updatedDate":"Sunday, December 19, 2021 at 2:31:27 PM Myanmar Time","createdDate":"Sunday, December 19, 2021 at 8:01:27 AM Myanmar Time","createdBy":"1","macId":11,"userCode":"PK-007"},{"key":{"brandCode":"11-016","compCode":"0010010","deptId":1},"brandName":"1PK*5PCS","updatedDate":"Sunday, December 19, 2021 at 4:39:30 PM Myanmar Time","createdDate":"Sunday, December 19, 2021 at 10:09:30 AM Myanmar Time","createdBy":"1","macId":11,"userCode":"PK-008"},{"key":{"brandCode":"12-001","compCode":"0010010","deptId":1},"brandName":"1bag*6pk*20pcs","updatedDate":"Sunday, December 19, 2021 at 9:27:33 AM Myanmar Time","createdDate":"Sunday, December 19, 2021 at 2:57:32 AM Myanmar Time","createdBy":"1","macId":12,"userCode":"17"},{"key":{"brandCode":"12-002","compCode":"0010010","deptId":1},"brandName":"1box*40pcs","updatedDate":"Sunday, December 19, 2021 at 9:35:14 AM Myanmar Time","createdDate":"Sunday, December 19, 2021 at 3:05:13 AM Myanmar Time","createdBy":"1","macId":12,"userCode":"18"},{"key":{"brandCode":"12-003","compCode":"0010010","deptId":1},"brandName":"1bag*12pk*6pcs","updatedDate":"Sunday, December 19, 2021 at 11:40:08 AM Myanmar Time","createdDate":"Sunday, December 19, 2021 at 5:10:08 AM Myanmar Time","createdBy":"1","macId":12,"userCode":"19"},{"key":{"brandCode":"12-004","compCode":"0010010","deptId":1},"brandName":"1bag*16pk*6pcs","updatedDate":"Sunday, December 19, 2021 at 1:51:06 PM Myanmar Time","createdDate":"Sunday, December 19, 2021 at 7:21:06 AM Myanmar Time","createdBy":"1","macId":12,"userCode":"20"},{"key":{"brandCode":"12-005","compCode":"0010010","deptId":1},"brandName":"1box*36pcs","updatedDate":"Sunday, December 19, 2021 at 1:56:47 PM Myanmar Time","createdDate":"Sunday, December 19, 2021 at 7:26:48 AM Myanmar Time","createdBy":"1","macId":12,"userCode":"21"},{"key":{"brandCode":"12-006","compCode":"0010010","deptId":1},"brandName":"1bag*15pk*10pcs","updatedDate":"Sunday, December 19, 2021 at 2:17:17 PM Myanmar Time","createdDate":"Sunday, December 19, 2021 at 7:47:17 AM Myanmar Time","createdBy":"1","macId":12,"userCode":"22"},{"key":{"brandCode":"12-007","compCode":"0010010","deptId":1},"brandName":"1bag*15pk*12pcs","updatedDate":"Sunday, December 19, 2021 at 2:25:28 PM Myanmar Time","createdDate":"Sunday, December 19, 2021 at 7:55:28 AM Myanmar Time","createdBy":"1","macId":12,"userCode":"23"},{"key":{"brandCode":"12-008","compCode":"0010010","deptId":1},"brandName":"1box*20pcs","updatedDate":"Sunday, December 19, 2021 at 3:38:25 PM Myanmar Time","createdDate":"Sunday, December 19, 2021 at 9:08:25 AM Myanmar Time","createdBy":"1","macId":12,"userCode":"25"},{"key":{"brandCode":"12-009","compCode":"0010010","deptId":1},"brandName":"1bag*10pk*12pcs","updatedDate":"Sunday, December 19, 2021 at 4:25:31 PM Myanmar Time","createdDate":"Sunday, December 19, 2021 at 9:55:31 AM Myanmar Time","createdBy":"1","macId":12,"userCode":"26"},{"key":{"brandCode":"12-010","compCode":"0010010","deptId":1},"brandName":"1bag*10pk*14pcs","updatedDate":"Sunday, December 19, 2021 at 4:25:48 PM Myanmar Time","createdDate":"Sunday, December 19, 2021 at 9:55:48 AM Myanmar Time","createdBy":"1","macId":12,"userCode":"27"},{"key":{"brandCode":"12-011","compCode":"0010010","deptId":1},"brandName":"1bag*6pk*10pcs","updatedDate":"Sunday, December 19, 2021 at 4:46:36 PM Myanmar Time","createdDate":"Sunday, December 19, 2021 at 10:16:36 AM Myanmar Time","createdBy":"1","macId":12,"userCode":"28"},{"key":{"brandCode":"12-012","compCode":"0010010","deptId":1},"brandName":"1bag*25kg","updatedDate":"Monday, December 20, 2021 at 11:29:27 AM Myanmar Time","createdDate":"Monday, December 20, 2021 at 4:59:27 AM Myanmar Time","createdBy":"1","macId":12,"userCode":"C-01"}]