[{"key":{"vouNo":"01-0100006-1222","compCode":"0010010","deptId":1},"status":"STATUS"},{"key":{"vouNo":"01-0100007-1222","compCode":"0010010","deptId":1},"status":"STATUS"},{"key":{"vouNo":"01-0200001-0123","compCode":"0010010","deptId":1},"status":"STATUS"},{"key":{"vouNo":"01-0200002-0123","compCode":"0010010","deptId":1},"status":"STATUS"},{"key":{"vouNo":"01-0200002-1222","compCode":"0010010","deptId":1},"status":"STATUS"},{"key":{"vouNo":"01-0200003-1222","compCode":"0010010","deptId":1},"status":"STATUS"},{"key":{"vouNo":"01-0300001-0123","compCode":"0010010","deptId":1},"status":"STATUS"},{"key":{"vouNo":"01-0300001-1222","compCode":"0010010","deptId":1},"status":"STATUS"},{"key":{"vouNo":"01-0300002-0123","compCode":"0010010","deptId":1},"status":"STATUS"},{"key":{"vouNo":"01-0300003-0123","compCode":"0010010","deptId":1},"status":"STATUS"},{"key":{"vouNo":"0100005-1222","compCode":"0010010","deptId":1},"status":"STATUS"},{"key":{"vouNo":"02-0700001-0123","compCode":"0010010","deptId":1},"status":"STATUS"},{"key":{"vouNo":"0200001-1222","compCode":"0010010","deptId":1},"status":"STATUS"}]